{
  "type": "Feature",
  "properties": {
    "date:inception_lower": "2024-06-17",
    "date:inception_upper": "2024-06-17",
    "flysfo:url": "https://www.sfomuseum.org/public-art/public-collection/color-horizons",
    "millsfield:wayfinding_detail": "DEP",
    "millsfield:wayfinding_kind": "HMT1",
    "sfo:level": 2,
    "sfomuseum:artist_dates": "b. 1982",
    "sfomuseum:artist_name": "Dana Hemenway",
    "sfomuseum:boardingarea": "B",
    "sfomuseum:building": "T1",
    "sfomuseum:category": "sculpture",
    "sfomuseum:collection": "Arts Commission",
    "sfomuseum:date": "2020",
    "sfomuseum:medium": "Wood, steel, rope, extension cords, glazed ceramics, LED lights",
    "sfomuseum:on_display": 1,
    "sfomuseum:placetype": "publicart",
    "sfomuseum:post_security": 0,
    "sfomuseum:subcategory": "ceiling sculpture",
    "wof:label": "The Color of Horizons",
    "wof:name": "The Color of Horizons",
    "wof:placetype": "venue",
    "wof:placetype_alt": [
      "publicart"
    ]
  },
  "geometry": {"coordinates":[-122.387011,37.614708],"type":"Point"}
}
