{
  "type": "Feature",
  "properties": {
    "date:inception_lower": "2024-06-17",
    "date:inception_upper": "2024-06-17",
    "flysfo:node": 3314,
    "flysfo:url": "https://www.sfomuseum.org/public-art/public-collection/peasants-parade",
    "iso:country": "US",
    "millsfield:wayfinding_detail": "D",
    "millsfield:wayfinding_kind": "T2",
    "sfac:artist": "Hoefer, Wade",
    "sfac:created_at": "01/01/1970 12:33:05 AM +0000",
    "sfac:credit_line": "Purchased by the San Francisco Art Commission for the San Francisco International Airport.",
    "sfac:display_dimensions": "64\" H X 120\" W",
    "sfac:location_description": "Airport : Terminal 2 : Gate 58 B",
    "sfac:medium": "Acrylic and sand on canvas",
    "sfac:revision": "2-2eade7175c260fa0e3e24351618e1788",
    "sfac:title": "The Peasant's Parade",
    "sfo:level": 2,
    "sfomuseum:artist_dates": "1951 - 2020",
    "sfomuseum:artist_name": "Wade Hoefer",
    "sfomuseum:boardingarea": "D",
    "sfomuseum:building": "T2",
    "sfomuseum:category": "painting",
    "sfomuseum:collection": "Arts Commission",
    "sfomuseum:date": "1985",
    "sfomuseum:description": "Three abstract gourds atop tree trunks.",
    "sfomuseum:is_sfo": 1,
    "sfomuseum:level": "2",
    "sfomuseum:medium": "Acrylic gel and sand on canvas",
    "sfomuseum:on_display": 1,
    "sfomuseum:placetype": "publicart",
    "sfomuseum:post_security": 1,
    "sfomuseum:terminal": "2",
    "sfomuseum:type": "painting",
    "wof:label": "Hoefer, Wade The Peasant's Parade",
    "wof:name": "The Peasant's Parade",
    "wof:placetype": "venue",
    "wof:placetype_alt": [
      "publicart"
    ]
  },
  "geometry": {"coordinates":[-122.38167777989301,37.61773804687223],"type":"Point"}
}
