{
  "type": "Feature",
  "properties": {
    "date:inception_lower": "2024-11-05",
    "date:inception_upper": "2024-11-05",
    "flysfo:node": 3339,
    "flysfo:url": "https://www.sfomuseum.org/public-art/public-collection/bird-technology",
    "iso:country": "US",
    "millsfield:wayfinding_detail": "G",
    "millsfield:wayfinding_kind": "ITB",
    "sfac:artist": "Garcia, Rupert",
    "sfac:created_at": "01/01/1970 12:33:20 AM +0000",
    "sfac:credit_line": "Commissioned for the San Francisco International Airport; Collection of the City and County of San Francisco.",
    "sfac:display_dimensions": "204 in. x 300 in.",
    "sfac:location_description": "Airport : IT : Boarding Area G : Gate G102",
    "sfac:medium": "Ceramic Tile",
    "sfac:revision": "2-6dd1df8169595adb8f74945cb1f22807",
    "sfac:title": "Bird Technology",
    "sfo:level": 2,
    "sfomuseum:artist_dates": "b. 1941",
    "sfomuseum:artist_name": "Rupert Garcia",
    "sfomuseum:boardingarea": "G",
    "sfomuseum:building": "IT",
    "sfomuseum:category": "mosaic",
    "sfomuseum:collection": "Arts Commission",
    "sfomuseum:date": "2000",
    "sfomuseum:description": "This hand-glazed tile work depicts a graceful silhouette of a bird in flight against a blue background and a geometric design in multi-colored squares to the right. The work refers to the importance of nature, as represented by the bird, and the importance of science and technology, as symbolized by the geometric patterns, in making human flight possible.",
    "sfomuseum:is_sfo": 1,
    "sfomuseum:level": "2",
    "sfomuseum:medium": "Hand-painted ceramic tile",
    "sfomuseum:on_display": 1,
    "sfomuseum:placetype": "publicart",
    "sfomuseum:post_security": 1,
    "sfomuseum:terminal": "IT",
    "sfomuseum:type": "mosaic",
    "wof:label": "Bird Technology (2024-11-05)",
    "wof:name": "Bird Technology",
    "wof:placetype": "venue",
    "wof:placetype_alt": [
      "publicart"
    ]
  },
  "geometry": {"coordinates":[-122.3929435962143,37.61862984433499],"type":"Point"}
}
