{
  "type": "Feature",
  "properties": {
    "date:inception_lower": "2020-05-01",
    "date:inception_upper": "2020-05-31",
    "iso:country": "US",
    "sfo:level": -1,
    "sfomuseum:building": "T1",
    "sfomuseum:collection": "Arts Commission",
    "sfomuseum:is_sfo": 1,
    "sfomuseum:medium": "oil on canvas mounted on wood",
    "sfomuseum:on_display": 1,
    "sfomuseum:placetype": "publicart",
    "sfomuseum:post_security": 0,
    "wof:label": "K1",
    "wof:name": "K1",
    "wof:placetype": "venue"
  },
  "geometry": {"coordinates":[-122.38515,37.613691],"type":"Point"}
}
