{
  "type": "Feature",
  "properties": {
    "sfo:level": 2,
    "sfomuseum:category": "photography",
    "sfomuseum:collection": "Arts Commission",
    "sfomuseum:medium": "archival pigment print",
    "sfomuseum:on_display": 1,
    "sfomuseum:placetype": "publicart",
    "sfomuseum:post_security": 1,
    "sfomuseum:subcategory": "archival pigment print",
    "wof:label": "Crowd at Texas Playhouse, September 10, 1958",
    "wof:name": "Crowd at Texas Playhouse, September 10, 1958",
    "wof:placetype": "venue",
    "wof:placetype_alt": "publicart"
  },
  "geometry": {"coordinates":[-122.383521,37.617574],"type":"Point"}
}
