{
  "type": "Feature",
  "properties": {
    "date:inception_lower": "2024-11-05",
    "date:inception_upper": "2024-11-05",
    "flysfo:node": 3279,
    "flysfo:url": "https://www.sfomuseum.org/public-art/public-collection/take",
    "iso:country": "US",
    "millsfield:wayfinding_detail": "G",
    "millsfield:wayfinding_kind": "ITB",
    "sfac:artist": "Liu, Hung",
    "sfac:created_at": "2006-2008",
    "sfac:location_description": "Airport : International Terminal : Gate A-5",
    "sfac:medium": "oil and pigmented ink with gesso",
    "sfac:revision": "2-4f9d4ad29401333300acf1328dfe6484",
    "sfac:title": "Take Off",
    "sfo:level": 2,
    "sfomuseum:artist_dates": "1948–2021",
    "sfomuseum:artist_name": "Hung Liu",
    "sfomuseum:boardingarea": "A",
    "sfomuseum:building": "IT",
    "sfomuseum:category": "mural",
    "sfomuseum:collection": "Arts Commission",
    "sfomuseum:date": "2006-2008",
    "sfomuseum:description": "This 17-by-28-foot multi-panel artwork depicts a young boy wading among the reeds in a river, discovering and chasing a water bird into flight. The center panel is flanked by two smaller images of birds from the Song Dynasty (960-1279), one taking off and the other perched.",
    "sfomuseum:is_sfo": 1,
    "sfomuseum:level": "2",
    "sfomuseum:medium": "Permanent ink and oil paint on wood",
    "sfomuseum:on_display": 1,
    "sfomuseum:placetype": "publicart",
    "sfomuseum:post_security": 1,
    "sfomuseum:terminal": "IT",
    "sfomuseum:type": "mural",
    "wfnd:placetype": "publicart",
    "wof:label": "Liu, Hung Take Off",
    "wof:name": "Take Off",
    "wof:placetype": "venue",
    "wof:placetype_alt": [
      "publicart"
    ]
  },
  "geometry": {"coordinates":[-122.38932821393864,37.61264509249442],"type":"Point"}
}
