{
  "type": "Feature",
  "properties": {
    "date:inception_lower": "2019-01-01",
    "date:inception_upper": "2019-12-31",
    "iso:country": "US",
    "sfo:level": -1,
    "sfomuseum:building": "Parking Garage",
    "sfomuseum:category": "light art",
    "sfomuseum:collection": "Arts Commission",
    "sfomuseum:is_sfo": 1,
    "sfomuseum:medium": "light, glass, steel",
    "sfomuseum:on_display": 1,
    "sfomuseum:placetype": "publicart",
    "sfomuseum:post_security": 0,
    "sfomuseum:subcategory": "neon",
    "wof:label": "Coding",
    "wof:name": "Coding",
    "wof:placetype": "venue"
  },
  "geometry": {"coordinates":[-122.40166,37.635661],"type":"Point"}
}
