{
  "type": "Feature",
  "properties": {
    "date:inception_lower": "2019-01-01",
    "date:inception_upper": "2019-12-31",
    "flysfo:url": "https://www.sfomuseum.org/public-art/public-collection/coding",
    "iso:country": "US",
    "millsfield:wayfinding_kind": "PRK",
    "sfo:level": 0,
    "sfo:max_level": 6,
    "sfo:min_level": 1,
    "sfomuseum:artist_dates": "b. 1961",
    "sfomuseum:artist_name": "Johanna Grawunder",
    "sfomuseum:building": "Parking Garage",
    "sfomuseum:category": "light art",
    "sfomuseum:collection": "Arts Commission",
    "sfomuseum:date": "2019",
    "sfomuseum:is_sfo": 1,
    "sfomuseum:medium": "Computer-controlled color-changing RBG LED light fixtures, glass painted steel panels",
    "sfomuseum:on_display": 1,
    "sfomuseum:placetype": "publicart",
    "sfomuseum:post_security": 0,
    "sfomuseum:subcategory": "neon",
    "wof:label": "Coding",
    "wof:name": "Coding",
    "wof:placetype": "venue",
    "wof:placetype_alt": [
      "publicart"
    ]
  },
  "geometry": {"coordinates":[-122.40166,37.635661],"type":"Point"}
}
