{
  "type": "Feature",
  "properties": {
    "date:inception_lower": "2020-05-01",
    "date:inception_upper": "2020-05-31",
    "flysfo:node": 21554,
    "flysfo:url": "https://www.flysfo.com/museum/public-art-collection?nid=21554",
    "iso:country": "US",
    "sfac:artist": "Rivera, Gustavo",
    "sfac:created_at": "01/01/1970 12:32:58 AM +0000",
    "sfac:credit_line": "Purchased by the San Francisco Art Commission for the San Francisco International Airport.",
    "sfac:display_dimensions": "66\" H X 75\" W",
    "sfac:location_description": "Airport : T3 : Boarding Area E : Gate 61",
    "sfac:medium": "Acrylic on canvas",
    "sfac:revision": "2-4cffed9659fab1df5f4fc62a5a9c5841",
    "sfac:title": "Azul, Azul Y Hacer",
    "sfo:level": 2,
    "sfomuseum:boardingarea": "E",
    "sfomuseum:building": "T3",
    "sfomuseum:category": "painting",
    "sfomuseum:collection": "Arts Commission",
    "sfomuseum:description": "Abstract painting with blue background.  Several shapes in red, white, black and blue.",
    "sfomuseum:is_sfo": 1,
    "sfomuseum:level": "2",
    "sfomuseum:medium": "Acrylic on canvas",
    "sfomuseum:on_display": 1,
    "sfomuseum:placetype": "publicart",
    "sfomuseum:post_security": 0,
    "sfomuseum:terminal": "3",
    "sfomuseum:type": "painting",
    "wof:label": "Rivera, Gustavo Azul, Azul y Hacer",
    "wof:name": "Azul, Azul y Hacer",
    "wof:placetype": "venue",
    "wof:placetype_alt": "publicart"
  },
  "geometry": {"coordinates":[-122.386247,37.618277],"type":"Point"}
}
