{
  "type": "Feature",
  "properties": {
    "date:inception_lower": "2021-05-25",
    "date:inception_upper": "2021-05-25",
    "sfo:level": 0,
    "sfomuseum:boardingarea": "B",
    "sfomuseum:building": "T1",
    "sfomuseum:category": "sculpture",
    "sfomuseum:collection": "Arts Commission",
    "sfomuseum:medium": "Oxidized bronze",
    "sfomuseum:on_display": 1,
    "sfomuseum:placetype": "publicart",
    "sfomuseum:post_security": 1,
    "sfomuseum:subcategory": "wall piece",
    "wof:label": "Unfolding Space (in Gold)",
    "wof:name": "Unfolding Space (in Gold)",
    "wof:placetype": "venue",
    "wof:placetype_alt": "publicart"
  },
  "geometry": {"coordinates":[-122.385186,37.611117],"type":"Point"}
}
