{
  "type": "Feature",
  "properties": {
    "date:inception_lower": "2020-05-01",
    "date:inception_upper": "2020-05-31",
    "iso:country": "US",
    "sfo:level": 3,
    "sfomuseum:boardingarea": "G",
    "sfomuseum:building": "IT",
    "sfomuseum:category": "sculpture",
    "sfomuseum:collection": "Arts Commission",
    "sfomuseum:is_sfo": 1,
    "sfomuseum:medium": "bronze",
    "sfomuseum:on_display": 1,
    "sfomuseum:placetype": "publicart",
    "sfomuseum:post_security": 1,
    "wof:label": "Turn",
    "wof:name": "Turn",
    "wof:placetype": "venue",
    "wof:placetype_alt": "publicart"
  },
  "geometry": {"coordinates":[-122.393323,37.618652],"type":"Point"}
}
