{
  "type": "Feature",
  "properties": {
    "date:inception_lower": "2020-05-01",
    "date:inception_upper": "2020-05-31",
    "flysfo:node": 5267,
    "flysfo:url": "https://www.flysfo.com/museum/public-art-collection?nid=5267",
    "iso:country": "US",
    "sfac:artist": "Loarca, Carlos",
    "sfac:created_at": "01/01/1970 12:32:58 AM +0000",
    "sfac:credit_line": "Purchased by the San Francisco Art Commission for the San Francisco International Airport.",
    "sfac:display_dimensions": "72\"H X 48\" W",
    "sfac:location_description": "Airport : T3 : Boarding Area E",
    "sfac:medium": "Acrylic on board",
    "sfac:revision": "2-1b7ae28390c3c7372f71713360f43ef7",
    "sfac:title": "Angulos en Todas Direciones",
    "sfomuseum:boardingarea": "E",
    "sfomuseum:building": "T3",
    "sfomuseum:category": "painting",
    "sfomuseum:collection": "Arts Commission",
    "sfomuseum:description": "Diptych - colorful abstract shapes.",
    "sfomuseum:is_sfo": 1,
    "sfomuseum:level": "2",
    "sfomuseum:medium": "Acrylic on board, diptych",
    "sfomuseum:on_display": 1,
    "sfomuseum:placetype": "publicart",
    "sfomuseum:post_security": 1,
    "sfomuseum:terminal": "3",
    "wof:label": "Ángulos en Todas las Direcciones",
    "wof:name": "Ángulos en Todas las Direcciones",
    "wof:placetype": "venue",
    "wof:placetype_alt": "publicart"
  },
  "geometry": {"coordinates":[-122.384402,37.619305],"type":"Point"}
}
