{
  "type": "Feature",
  "properties": {
    "date:inception_lower": "2020-05-01",
    "date:inception_upper": "2020-05-31",
    "flysfo:node": 21556,
    "flysfo:url": "https://www.flysfo.com/museum/public-art-collection?nid=21556",
    "iso:country": "US",
    "sfomuseum:boardingarea": "E",
    "sfomuseum:building": "T3",
    "sfomuseum:category": "painting",
    "sfomuseum:collection": "Arts Commission",
    "sfomuseum:description": "Horizontal bands of marbled color washes.",
    "sfomuseum:is_sfo": 1,
    "sfomuseum:level": "1",
    "sfomuseum:medium": "oil on canvas",
    "sfomuseum:on_display": 1,
    "sfomuseum:placetype": "publicart",
    "sfomuseum:post_security": 0,
    "sfomuseum:terminal": "3",
    "sfomuseum:type": "painting",
    "wof:label": "Simpson, David Storm, Stars, and Stripes",
    "wof:name": "Storm, Stars, and Stripes",
    "wof:placetype": "venue",
    "wof:placetype_alt": "publicart"
  },
  "geometry": {"coordinates":[-122.38482,37.618077],"type":"Point"}
}
