{
  "type": "Feature",
  "properties": {
    "date:inception_lower": "2020-05-01",
    "date:inception_upper": "2020-05-31",
    "flysfo:node": 3286,
    "flysfo:url": "https://www.flysfo.com/museum/public-art-collection?nid=3286",
    "iso:country": "US",
    "sfac:artist": "Rojas, Clare",
    "sfac:created_at": "2008-2009",
    "sfac:location_description": "Airport : International Terminal : Boarding Area G",
    "sfac:medium": "Paint and pigmented ink",
    "sfac:revision": "2-81f046aef5884ef85f60c1c9ff0b3c6f",
    "sfac:title": "Blue Deer",
    "sfomuseum:boardingarea": "G",
    "sfomuseum:building": "IT",
    "sfomuseum:category": "painting",
    "sfomuseum:collection": "Arts Commission",
    "sfomuseum:description": "Blue Deer is a large-scale painting that depicts a woman cajoling a small deer out from underneath two trees. The imagery was derived from a children’s book written and illustrated by Rojas called Blue Deer and Red Fox. With its use of vivid geometric shapes and the block patterns of traditional quilts, Blue Deer reflects Rojas’ deep interest in American folk art, quilting and storytelling.",
    "sfomuseum:is_sfo": 1,
    "sfomuseum:level": "2",
    "sfomuseum:medium": "Oil and pigmented ink with gesso ground on wood panels",
    "sfomuseum:on_display": 1,
    "sfomuseum:placetype": "publicart",
    "sfomuseum:post_security": 1,
    "sfomuseum:terminal": "IT",
    "sfomuseum:type": "painting",
    "wof:label": "Rojas, Claire Blue Deer",
    "wof:name": "Blue Deer",
    "wof:placetype": "venue",
    "wof:placetype_alt": "publicart"
  },
  "geometry": {"coordinates":[-122.391965,37.617988],"type":"Point"}
}
