{
  "type": "Feature",
  "properties": {
    "date:inception_lower": "2024-11-05",
    "date:inception_upper": "2024-11-05",
    "millsfield:wayfinding_detail": "A",
    "millsfield:wayfinding_kind": "ITB",
    "sfo:level": 2,
    "sfomuseum:artist_dates": "b. 1960",
    "sfomuseum:artist_name": "Linda Geary",
    "sfomuseum:boardingarea": "A",
    "sfomuseum:building": "IT",
    "sfomuseum:category": "mosaic",
    "sfomuseum:collection": "Arts Commission",
    "sfomuseum:date": "2020",
    "sfomuseum:medium": "ceramic, mosaic mural",
    "sfomuseum:on_display": 1,
    "sfomuseum:placetype": "publicart",
    "sfomuseum:post_security": 1,
    "wfnd:detail": "A",
    "wfnd:is_restricted": true,
    "wfnd:kind": "ITB",
    "wfnd:level": 2,
    "wfnd:placetype": "publicart",
    "wof:label": "River",
    "wof:name": "River",
    "wof:placetype": "venue",
    "wof:placetype_alt": [
      "publicart"
    ]
  },
  "geometry": {"coordinates":[-122.38869793683125,37.61425197717583],"type":"Point"}
}
