{
  "type": "Feature",
  "properties": {
    "date:inception_lower": "2024-11-05",
    "date:inception_upper": "2024-11-05",
    "millsfield:wayfinding_detail": "D",
    "millsfield:wayfinding_kind": "T2",
    "sfo:level": 2,
    "sfomuseum:artist_dates": "b. 1951",
    "sfomuseum:artist_name": "Michael Jang",
    "sfomuseum:category": "photography",
    "sfomuseum:collection": "Arts Commission",
    "sfomuseum:date": "1973",
    "sfomuseum:medium": "archival pigment print",
    "sfomuseum:on_display": 1,
    "sfomuseum:placetype": "publicart",
    "sfomuseum:post_security": 0,
    "sfomuseum:subcategory": "archival pigment print",
    "wfnd:detail": "D",
    "wfnd:is_restricted": false,
    "wfnd:kind": "T2",
    "wfnd:level": 2,
    "wfnd:placetype": "publicart",
    "wof:label": "At Home with the Jangs  (2024-11-05)",
    "wof:name": "At Home with the Jangs ",
    "wof:placetype": "venue",
    "wof:placetype_alt": [
      "publicart"
    ]
  },
  "geometry": {"coordinates":[-122.38336291831102,37.617497021580775],"type":"Point"}
}
