{
  "type": "Feature",
  "properties": {
    "date:inception_lower": "2019-07-01",
    "date:inception_upper": "2019-07-31",
    "iso:country": "US",
    "sfo:level": 4,
    "sfomuseum:building": "Hotel",
    "sfomuseum:category": "print",
    "sfomuseum:collection": "Arts Commission",
    "sfomuseum:is_current": -2,
    "sfomuseum:is_sfo": 1,
    "sfomuseum:medium": "Paper, ink",
    "sfomuseum:on_display": 1,
    "sfomuseum:placetype": "publicart",
    "sfomuseum:post_security": 0,
    "sfomuseum:subcategory": "etching",
    "wof:label": "Untitled/ print no. 79.65-6/9",
    "wof:name": "Untitled/ print no. 79.65-6/9",
    "wof:placetype": "venue",
    "wof:placetype_alt": "publicart"
  },
  "geometry": {"coordinates":[-122.39364687113485,37.61318327373003],"type":"Point"}
}
