{
  "type": "Feature",
  "properties": {
    "date:inception_lower": "2024-11-05",
    "date:inception_upper": "2024-11-05",
    "millsfield:wayfinding_detail": "B",
    "millsfield:wayfinding_kind": "HMT1",
    "sfo:level": 2,
    "sfomuseum:artist_dates": "b. 1962",
    "sfomuseum:artist_name": "Spencer Finch",
    "sfomuseum:boardingarea": "B",
    "sfomuseum:building": "T1",
    "sfomuseum:category": "sculpture",
    "sfomuseum:collection": "Arts Commission",
    "sfomuseum:date": "2019",
    "sfomuseum:medium": "Filters, fixtures, LED tubes",
    "sfomuseum:on_display": 1,
    "sfomuseum:placetype": "publicart",
    "sfomuseum:post_security": 1,
    "sfomuseum:subcategory": "ceiling sculpture",
    "wof:label": "Orion (2024-11-05)",
    "wof:name": "Orion",
    "wof:placetype": "venue",
    "wof:placetype_alt": [
      "publicart"
    ]
  },
  "geometry": {"coordinates":[-122.38599386051912,37.61076159654855],"type":"Point"}
}
