{
  "type": "Feature",
  "properties": {
    "date:inception_lower": "2024-11-05",
    "date:inception_upper": "2024-11-05",
    "flysfo:url": "https://www.sfomuseum.org/public-art/public-collection/golden-gate-bridge-22700-455-pm-41700-401-pm-and-3401-730-pm",
    "iso:country": "US",
    "millsfield:wayfinding_kind": "GHH",
    "sfo:level": 2,
    "sfomuseum:artist_dates": "b. 1949",
    "sfomuseum:artist_name": "Richard Misrach",
    "sfomuseum:building": "Hotel",
    "sfomuseum:collection": "Arts Commission",
    "sfomuseum:date": "2000",
    "sfomuseum:is_sfo": 1,
    "sfomuseum:on_display": 1,
    "sfomuseum:placetype": "publicart",
    "sfomuseum:post_security": 0,
    "wfnd:detail": "GHH",
    "wfnd:is_restricted": false,
    "wfnd:kind": "GHH",
    "wfnd:level": 2,
    "wfnd:placetype": "publicart",
    "wof:label": "Golden Gate Bridge, 4.17.00, 4:01 pm",
    "wof:name": "Golden Gate Bridge, 4.17.00, 4:01 pm",
    "wof:placetype": "venue",
    "wof:placetype_alt": [
      "publicart"
    ]
  },
  "geometry": {"coordinates":[-122.39408215527395,37.612854591418795],"type":"Point"}
}
