{
  "type": "Feature",
  "properties": {
    "date:inception_lower": "2021-05-25",
    "date:inception_upper": "2021-05-25",
    "flysfo:node": 3281,
    "flysfo:url": "https://www.flysfo.com/museum/public-art-collection?nid=3281",
    "iso:country": "US",
    "sfac:artist": "Chagoya, Enrique",
    "sfac:created_at": "01/01/1970 12:33:19 AM +0000",
    "sfac:credit_line": "Commissioned by the Public Art Program for San Francisco International Airport; Collection of the City and County of San Francisco",
    "sfac:display_dimensions": "16' H X 24' W",
    "sfac:location_description": "Airport : IT : Boarding Area A, Gate A8",
    "sfac:medium": "glass tiles",
    "sfac:revision": "2-7dceb0baacb57541f908dcc58b4fdcf0",
    "sfac:title": "Love Letters",
    "sfo:level": 2,
    "sfomuseum:boardingarea": "A",
    "sfomuseum:building": "IT",
    "sfomuseum:category": "mural",
    "sfomuseum:collection": "Arts Commission",
    "sfomuseum:description": "This 16-by-24-foot mural of glass panels is a reproduction of a pastel drawing depicting paper boats set adrift on a body of water with hand written excerpts from published poetry expressing emotions such as love, hope, longing, and nostalgia, all written in their original language.",
    "sfomuseum:is_sfo": 1,
    "sfomuseum:level": "2",
    "sfomuseum:medium": "Custom graphic, laminated glass",
    "sfomuseum:on_display": 1,
    "sfomuseum:placetype": "publicart",
    "sfomuseum:post_security": 1,
    "sfomuseum:terminal": "IT",
    "sfomuseum:type": "mural",
    "wof:label": "Chagoya, Enrique Love Letters",
    "wof:name": "Love Letters",
    "wof:placetype": "venue",
    "wof:placetype_alt": "publicart"
  },
  "geometry": {"coordinates":[-122.390235,37.611816],"type":"Point"}
}
