{
  "type": "Feature",
  "properties": {
    "date:inception_lower": "2020-05-01",
    "date:inception_upper": "2020-05-31",
    "flysfo:node": 21552,
    "flysfo:url": "https://www.flysfo.com/museum/public-art-collection?nid=21552",
    "iso:country": "US",
    "sfo:level": -1,
    "sfomuseum:boardingarea": "E ",
    "sfomuseum:building": "T3",
    "sfomuseum:category": "print",
    "sfomuseum:collection": "Arts Commission",
    "sfomuseum:is_sfo": 1,
    "sfomuseum:level": "2",
    "sfomuseum:medium": "pigment print on archival paper",
    "sfomuseum:on_display": 1,
    "sfomuseum:placetype": "publicart",
    "sfomuseum:post_security": 1,
    "sfomuseum:terminal": "3",
    "sfomuseum:type": "print",
    "wof:label": "Everywhere All At Once",
    "wof:name": "Everywhere All At Once",
    "wof:placetype": "venue",
    "wof:placetype_alt": "publicart"
  },
  "geometry": {"coordinates":[-122.38587097669938,37.61856312123068],"type":"Point"}
}
