{
  "type": "Feature",
  "properties": {
    "sfo:level": 2,
    "sfomuseum:category": "photography",
    "sfomuseum:collection": "Arts Commission",
    "sfomuseum:medium": "archival pigment print",
    "sfomuseum:on_display": 1,
    "sfomuseum:placetype": "publicart",
    "sfomuseum:post_security": 1,
    "sfomuseum:subcategory": "archival pigment print",
    "wof:label": "Young Couple at Carnaval (from Public Matters, 1982-1988)",
    "wof:name": "Young Couple at Carnaval (from Public Matters, 1982-1988)",
    "wof:placetype": "venue",
    "wof:placetype_alt": "publicart"
  },
  "geometry": {"coordinates":[-122.383411,37.61761],"type":"Point"}
}
