{
  "type": "Feature",
  "properties": {
    "millsfield:wayfinding_detail": "D",
    "millsfield:wayfinding_kind": "T2",
    "sfo:level": 2,
    "sfomuseum:artist_dates": "b. 1952",
    "sfomuseum:artist_name": "Janet Delaney",
    "sfomuseum:category": "photography",
    "sfomuseum:collection": "Arts Commission",
    "sfomuseum:date": "1984",
    "sfomuseum:medium": "archival pigment print",
    "sfomuseum:on_display": 1,
    "sfomuseum:placetype": "publicart",
    "sfomuseum:post_security": 0,
    "sfomuseum:subcategory": "archival pigment print",
    "wof:label": "Young Couple at Carnaval (from Public Matters, 1982-1988)",
    "wof:name": "Young Couple at Carnaval (from Public Matters, 1982-1988)",
    "wof:placetype": "venue",
    "wof:placetype_alt": [
      "publicart"
    ]
  },
  "geometry": {"coordinates":[-122.38343768464297,37.61753353955838],"type":"Point"}
}
