{
  "type": "Feature",
  "properties": {
    "date:inception_lower": "2024-06-17",
    "date:inception_upper": "2024-06-17",
    "millsfield:wayfinding_detail": "B",
    "millsfield:wayfinding_kind": "HMT1",
    "sfo:level": 2,
    "sfomuseum:artist_dates": "b. 1971",
    "sfomuseum:artist_name": "Yorgo Alexopoulos",
    "sfomuseum:boardingarea": "B",
    "sfomuseum:building": "T1",
    "sfomuseum:category": "video",
    "sfomuseum:collection": "Arts Commission",
    "sfomuseum:date": "2018",
    "sfomuseum:medium": "Two channel digital animation on 4K LCD displays, aspect ratio 32:5 (6:40), synchronized media players. 11 minute, 30 second infinite loop (on 2 screens).",
    "sfomuseum:on_display": 1,
    "sfomuseum:placetype": "publicart",
    "sfomuseum:post_security": 1,
    "wof:label": "Split (2024-06-17)",
    "wof:name": "Split",
    "wof:placetype": "venue",
    "wof:placetype_alt": [
      "publicart"
    ]
  },
  "geometry": {"coordinates":[-122.38538100530039,37.61382868431113],"type":"Point"}
}
