{
  "type": "Feature",
  "properties": {
    "date:inception_lower": "2024-11-05",
    "date:inception_upper": "2024-11-05",
    "flysfo:url": "https://www.sfomuseum.org/public-art/public-collection/yale-portfolio",
    "iso:country": "US",
    "millsfield:wayfinding_detail": "DEP",
    "millsfield:wayfinding_kind": "HMT1",
    "sfo:level": 2,
    "sfomuseum:artist_dates": "1921 - 2013",
    "sfomuseum:artist_name": "Frank Lobdell",
    "sfomuseum:boardingarea": "B",
    "sfomuseum:building": "T1",
    "sfomuseum:category": "print",
    "sfomuseum:collection": "Arts Commission",
    "sfomuseum:date": "1992",
    "sfomuseum:is_sfo": 1,
    "sfomuseum:medium": "Etchings (5)",
    "sfomuseum:on_display": 1,
    "sfomuseum:placetype": "publicart",
    "sfomuseum:post_security": 1,
    "sfomuseum:subcategory": "etching",
    "wof:label": "Yale Portfolio",
    "wof:name": "Yale Portfolio",
    "wof:placetype": "venue",
    "wof:placetype_alt": [
      "publicart"
    ]
  },
  "geometry": {"coordinates":[-122.3855071878296,37.611186112671746],"type":"Point"}
}
