{
  "type": "Feature",
  "properties": {
    "date:inception_lower": "2021-05-25",
    "date:inception_upper": "2021-05-25",
    "flysfo:node": 21551,
    "flysfo:url": "https://www.flysfo.com/museum/public-art-collection?nid=21551",
    "iso:country": "US",
    "millsfield:wayfinding_detail": "C",
    "millsfield:wayfinding_kind": "T1",
    "sfo:level": 2,
    "sfomuseum:boardingarea": "C",
    "sfomuseum:building": "T1",
    "sfomuseum:category": "sculpture",
    "sfomuseum:collection": "Arts Commission",
    "sfomuseum:is_sfo": 1,
    "sfomuseum:level": "2",
    "sfomuseum:medium": "fiberglass-reinforced plastic, stainless steel",
    "sfomuseum:on_display": 1,
    "sfomuseum:placetype": "publicart",
    "sfomuseum:post_security": 0,
    "sfomuseum:subcategory": "floor installation",
    "sfomuseum:terminal": "1",
    "sfomuseum:type": "sculpture",
    "wof:label": "High Heels for Going to Heaven ",
    "wof:name": "High Heels for Going to Heaven ",
    "wof:placetype": "venue",
    "wof:placetype_alt": "publicart"
  },
  "geometry": {"coordinates":[-122.383842,37.615732],"type":"Point"}
}
