{
  "type": "Feature",
  "properties": {
    "millsfield:wayfinding_kind": "CAC",
    "sfo:level": 2,
    "sfomuseum:building": "CAC",
    "sfomuseum:category": "photography",
    "sfomuseum:collection": "Arts Commission",
    "sfomuseum:medium": "archival pigment print",
    "sfomuseum:on_display": 1,
    "sfomuseum:placetype": "publicart",
    "sfomuseum:post_security": 1,
    "sfomuseum:subcategory": "archival pigment print",
    "wof:label": "Public Transit Areas #6",
    "wof:name": "Public Transit Areas #6",
    "wof:placetype": "venue",
    "wof:placetype_alt": "publicart"
  },
  "geometry": {"coordinates":[-122.383407,37.6176],"type":"Point"}
}
