{
  "type": "Feature",
  "properties": {
    "millsfield:wayfinding_kind": "CAC",
    "sfo:level": 2,
    "sfomuseum:artist_dates": "b. 1947",
    "sfomuseum:artist_name": "Anthony Hernandez",
    "sfomuseum:building": "CAC",
    "sfomuseum:category": "photography",
    "sfomuseum:collection": "Arts Commission",
    "sfomuseum:date": "1979",
    "sfomuseum:medium": "archival pigment print",
    "sfomuseum:on_display": 1,
    "sfomuseum:placetype": "publicart",
    "sfomuseum:post_security": 0,
    "sfomuseum:subcategory": "archival pigment print",
    "wof:label": "Public Transit Areas #6",
    "wof:name": "Public Transit Areas #6",
    "wof:placetype": "venue",
    "wof:placetype_alt": [
      "publicart"
    ]
  },
  "geometry": {"coordinates":[-122.38361129210946,37.61759473167237],"type":"Point"}
}
