{
  "type": "Feature",
  "properties": {
    "date:inception_lower": "2019-01-01",
    "date:inception_upper": "2019-12-31",
    "iso:country": "US",
    "sfo:level": 1,
    "sfomuseum:building": "Hotel",
    "sfomuseum:category": "mosaic",
    "sfomuseum:collection": "Arts Commission",
    "sfomuseum:is_sfo": 1,
    "sfomuseum:medium": "hand-cut glass, stone mosaic",
    "sfomuseum:on_display": 1,
    "sfomuseum:placetype": "publicart",
    "sfomuseum:post_security": 0,
    "wof:label": "Green Map",
    "wof:name": "Green Map",
    "wof:placetype": "venue"
  },
  "geometry": {"coordinates":[-122.39378617604558,37.6130408027986],"type":"Point"}
}
