{
  "type": "Feature",
  "properties": {
    "date:inception_lower": "2019-01-01",
    "date:inception_upper": "2019-12-31",
    "flysfo:url": "https://www.sfomuseum.org/public-art/public-collection/green-map",
    "iso:country": "US",
    "sfo:level": 0,
    "sfomuseum:building": "Hotel",
    "sfomuseum:category": "mosaic",
    "sfomuseum:collection": "Arts Commission",
    "sfomuseum:is_sfo": 1,
    "sfomuseum:medium": "hand-cut glass, stone mosaic",
    "sfomuseum:on_display": 1,
    "sfomuseum:placetype": "publicart",
    "sfomuseum:post_security": 0,
    "wof:label": "Green Map",
    "wof:name": "Green Map",
    "wof:placetype": "venue",
    "wof:placetype_alt": "publicart"
  },
  "geometry": {"coordinates":[-122.393786,37.613041],"type":"Point"}
}
