{
  "type": "Feature",
  "properties": {
    "date:inception_lower": "2024-11-05",
    "date:inception_upper": "2024-11-05",
    "millsfield:wayfinding_detail": "D",
    "millsfield:wayfinding_kind": "T2",
    "sfo:level": 2,
    "sfomuseum:category": "photography",
    "sfomuseum:collection": "Arts Commission",
    "sfomuseum:date": "c. 1950s",
    "sfomuseum:medium": "archival pigment print",
    "sfomuseum:on_display": 1,
    "sfomuseum:placetype": "publicart",
    "sfomuseum:post_security": 0,
    "sfomuseum:subcategory": "archival pigment print",
    "wfnd:detail": "T2",
    "wfnd:is_restricted": false,
    "wfnd:kind": "T2",
    "wfnd:level": 2,
    "wfnd:placetype": "publicart",
    "wof:label": "Jam Session Inside Bop City, 1951 (2024-11-05)",
    "wof:name": "Jam Session Inside Bop City, 1951",
    "wof:placetype": "venue",
    "wof:placetype_alt": [
      "publicart"
    ]
  },
  "geometry": {"coordinates":[-122.3835641797193,37.61758013609937],"type":"Point"}
}
