{
  "type": "Feature",
  "properties": {
    "millsfield:wayfinding_detail": "D",
    "millsfield:wayfinding_kind": "T2",
    "sfo:level": 2,
    "sfomuseum:category": "photography",
    "sfomuseum:collection": "Arts Commission",
    "sfomuseum:medium": "archival pigment print",
    "sfomuseum:on_display": 1,
    "sfomuseum:placetype": "publicart",
    "sfomuseum:post_security": 1,
    "sfomuseum:subcategory": "archival pigment print",
    "wof:label": "Rhythm Records, 1980 Sutter Street",
    "wof:name": "Rhythm Records, 1980 Sutter Street",
    "wof:placetype": "venue",
    "wof:placetype_alt": "publicart"
  },
  "geometry": {"coordinates":[-122.383549,37.61763],"type":"Point"}
}
