{
  "type": "Feature",
  "properties": {
    "iso:country":"US",
    "sfac:artist":"Noguchi, Isamu",
    "sfac:created_at":"01/01/1970 12:32:25 AM +0000",
    "sfac:credit_line":"Purchased by the San Francisco Art Commission for the San Francisco International Airport",
    "sfac:display_dimensions":"61\" H X 21 1/2\" W X 15 1/4\" D",
    "sfac:location_description":"Airport : T1 : Boarding Area C : Gate 45",
    "sfac:medium":"Cast bronze with black patina",
    "sfac:revision":"2-93b27476039afded6c595a3238889881",
    "sfac:title":"Figure",
    "sfomuseum:description":"Five organically shaped forms interlocking to create a fluid, graceful sculpture.  Original casting 1945; recast in 1973.",
    "sfomuseum:is_sfo":1,
    "sfomuseum:medium":"Cast bronze with black patina",
    "sfomuseum:on_display":1,
    "sfomuseum:placetype":"publicart",
    "sfomuseum:post_security":1,
    "sfomuseum:type":"sculpture",
    "wof:name":"Figure",
    "wof:placetype":"venue",
    "wof:placetype_alt":"publicart"
},
  "geometry": {"coordinates":[-122.38277614116669,37.61500904418947],"type":"Point"}
}